MANIFEST.in
README.rst
setup.cfg
setup.py
chatbot_script.egg-info/PKG-INFO
chatbot_script.egg-info/SOURCES.txt
chatbot_script.egg-info/dependency_links.txt
chatbot_script.egg-info/entry_points.txt
chatbot_script.egg-info/requires.txt
chatbot_script.egg-info/top_level.txt
chatbotx1/AWNDatabaseManagement.py
chatbotx1/Female_chatbot.py
chatbotx1/Male_chatbot.py
chatbotx1/__init__.py
chatbotx1/ar_autocorrectlist.py
chatbotx1/ar_ctype.py
chatbotx1/ar_ghalat.py
chatbotx1/arabic_const.py
chatbotx1/main_chatbot.py
chatbotx1/normalize.py
chatbotx1/stem_const.py
chatbotx1/stemming.py
chatbotx1/DB/__init__.py
chatbotx1/stanford-postagger-full-2015-04-20/__init__.py
chatbotx1/stanford-postagger-full-2015-04-20/data/__init__.py
chatbotx1/stanford-postagger-full-2015-04-20/models/__init__.py