Metadata-Version: 1.1
Name: chatbot-script
Version: 1.20.0
Summary: is a simple chatbot_script that uses simple matching 
Home-page: https://github.com/pypi/chatbot_script
Author: UNKNOWN
Author-email: UNKNOWN
License: MIT
Keywords: sample setuptools development
Platform: UNKNOWN
Classifier: Development Status :: 3 - Alpha
Classifier: Intended Audience :: Developers
Classifier: Topic :: Software Development :: Build Tools
Classifier: License :: OSI Approved :: MIT License
Classifier: Programming Language :: Python :: 2
Classifier: Programming Language :: Python :: 2.6
Classifier: Programming Language :: Python :: 2.7
Classifier: Programming Language :: Python :: 3
Classifier: Programming Language :: Python :: 3.3
Classifier: Programming Language :: Python :: 3.4
Classifier: Programming Language :: Python :: 3.5
